<decorators defaultdir="/decorators">
    <excludes>
        <pattern>/40*.jsp</pattern>
        <pattern>/*ajax=true*</pattern>
        <pattern>/struts/*</pattern>
        <pattern>/resources/*</pattern>
    </excludes> 
    
    <decorator name="anonymousdefault" page="anonymousdefault.jsp">
        <pattern>/login</pattern>
        <pattern>/signup</pattern>
    </decorator>
    
    <decorator name="default" page="default.jsp">
        <pattern>/*</pattern>
    </decorator>
    
</decorators>
